evaengine/__init__.py
evaengine/client.py
evaengine/exceptions.py
evaengine/models.py
evaengine-0.1.2.dist-info/LICENSE
evaengine-0.1.2.dist-info/METADATA
evaengine-0.1.2.dist-info/WHEEL
evaengine-0.1.2.dist-info/top_level.txt
evaengine-0.1.2.dist-info/RECORD
